pytokei-0.2.0.dist-info/METADATA
pytokei-0.2.0.dist-info/WHEEL
pytokei-0.2.0.dist-info/entry_points.txt
pytokei-0.2.0.dist-info/license_files/LICENSE
pytokei/_pytokei.pyi
pytokei/__init__.py
pytokei/cli.py
pytokei/py.typed
pytokei/_pytokei.abi3.so
pytokei-0.2.0.dist-info/RECORD
