Metadata-Version: 2.1
Name: pytokei
Version: 0.2.0
Classifier: Programming Language :: Python :: 3.7
Classifier: Programming Language :: Python :: 3.8
Classifier: Programming Language :: Python :: 3.9
Classifier: Programming Language :: Python :: 3.10
Classifier: Programming Language :: Python :: 3.11
Classifier: Intended Audience :: Developers
Classifier: License :: OSI Approved :: MIT License
Classifier: Operating System :: POSIX :: Linux
Classifier: Operating System :: Microsoft :: Windows
Classifier: Operating System :: MacOS
Classifier: Topic :: Software Development :: Libraries :: Python Modules
Requires-Dist: typer>=0.7.0; extra == 'cli'
Requires-Dist: rich>=13.3.0; extra == 'cli'
Provides-Extra: cli
License-File: LICENSE
Summary: Python bindings to tokei, the Rust library to count code quickly.
Author-email: Agustin Piqueres <agustin.piqueres@gmail.com>
License: MIT
Requires-Python: >=3.7
Project-URL: Homepage, https://github.com/plaguss/pytokei
Project-URL: Documentation, https://plaguss.github.io/pytokei/
Project-URL: Source, https://github.com/plaguss/pytokei
